README.md
setup.py
docketter/__init__.py
docketter.egg-info/PKG-INFO
docketter.egg-info/SOURCES.txt
docketter.egg-info/dependency_links.txt
docketter.egg-info/top_level.txt