Metadata-Version: 1.0
Name: docketter
Version: 1.0.1
Summary: Python library and CLI to manage multiple docker-compose files.
Home-page: https://github.com/Michotastico/docketter
Author: Michel Llorens
Author-email: mllorens@protonmail.com
License: MIT
Platform: UNKNOWN
